factgridbot/__init__.py
factgridbot/bot.py
factgridbot/cli.py
factgridbot/factgrid.py
factgridbot/wikibase.py
factgridbot/wikidata.py
factgridbot/models/__init__.py
factgridbot/models/auth.py
factgridbot/models/error.py
factgridbot/models/property_mapping.py
factgridbot-0.1.0.dist-info/METADATA
factgridbot-0.1.0.dist-info/WHEEL
factgridbot-0.1.0.dist-info/entry_points.txt
factgridbot-0.1.0.dist-info/licenses/LICENSE
factgridbot-0.1.0.dist-info/RECORD
