Metadata-Version: 2.4
Name: FactGridBot
Version: 0.1.0
Summary: A specialized Wikibase bot designed to synchronize and manage data between Wikidata and FactGrid.
Author-email: tholzheim <tim.holzheim@rwth-aachen.de>
License-Expression: Apache-2.0
License-File: LICENSE
Classifier: Development Status :: 5 - Production/Stable
Classifier: Intended Audience :: Developers
Classifier: License :: OSI Approved :: Apache Software License
Classifier: Operating System :: OS Independent
Classifier: Programming Language :: Python
Classifier: Programming Language :: Python :: 3 :: Only
Classifier: Programming Language :: Python :: 3.10
Classifier: Programming Language :: Python :: 3.11
Classifier: Programming Language :: Python :: 3.12
Classifier: Programming Language :: Python :: 3.13
Requires-Python: >=3.10
Requires-Dist: pydantic>=2.10.2
Requires-Dist: rich>=13.9.4
Requires-Dist: sparqlwrapper>=2.0.0
Requires-Dist: typer>=0.13.1
Requires-Dist: wikibaseintegrator>=0.12.10
